{
  "release_day": 6,
  "avg_rating_per_demo": {
    "aged_45+": 6.8,
    "top_1000_voters": 6.5,
    "males_under_18": 7.3,
    "imdb_staff": 6.4,
    "males_aged_18-29": 6.8,
    "imdb_users": 6.8,
    "males_aged_45+": 6.7,
    "aged_18-29": 6.8,
    "us_users": 6.9,
    "females_aged_30-44": 6.6,
    "males": 6.8,
    "females": 6.7,
    "females_aged_45+": 7.0,
    "non-us_users": 6.7,
    "females_aged_18-29": 6.7,
    "females_under_18": 7.3,
    "aged_30-44": 6.7,
    "aged_under_18": 7.3,
    "males_aged_30-44": 6.7
  },
  "closing_date": {
    "month": 1,
    "year": 2014,
    "day": 31,
    "__type__": "datetime.date"
  },
  "metascore": 63,
  "num_weekends": 9,
  "rating_count": 87095,
  "gross_income": 11326836,
  "max_screens": 2101,
  "opening_weekend_screens": 2101,
  "screens_by_weekend": [
    2101,
    2101,
    728,
    102,
    59,
    37,
    97,
    74,
    36
  ],
  "opening_weekend_income": 5220288,
  "release_year": 2013,
  "imdb_user_reviews": [
    {
      "contents": "Still an accurate portrait of many towns in America today",
      "score": 10,
      "user": "T Crossman",
      "review_date": {
        "month": 12,
        "year": 2013,
        "day": 6,
        "__type__": "datetime.date"
      }
    },
    {
      "contents": "A powerful film with among the best screen performances I've seen",
      "score": 9,
      "user": "nanvan108",
      "review_date": {
        "month": 12,
        "year": 2013,
        "day": 2,
        "__type__": "datetime.date"
      }
    },
    {
      "contents": "Fine cast, failure of a script",
      "score": 5,
      "user": "Aaron Widera",
      "review_date": {
        "month": 12,
        "year": 2013,
        "day": 15,
        "__type__": "datetime.date"
      }
    },
    {
      "contents": "In the vein of The Deer Hunter, Out of the Furnace captures the hopelessness of a nation",
      "score": 9,
      "user": "trublu215",
      "review_date": {
        "month": 11,
        "year": 2013,
        "day": 21,
        "__type__": "datetime.date"
      }
    },
    {
      "contents": "Very Well Done",
      "score": 9,
      "user": "edm-the_red",
      "review_date": {
        "month": 12,
        "year": 2013,
        "day": 10,
        "__type__": "datetime.date"
      }
    },
    {
      "contents": "A Promising Start That Leads to Run-Of-The-Mill Fare",
      "score": 7,
      "user": "FilmMuscle",
      "review_date": {
        "month": 12,
        "year": 2013,
        "day": 8,
        "__type__": "datetime.date"
      }
    },
    {
      "contents": "Bale at his best...",
      "score": 8,
      "user": "cyberstud87",
      "review_date": {
        "month": 12,
        "year": 2013,
        "day": 25,
        "__type__": "datetime.date"
      }
    },
    {
      "contents": "Great Action Turns Into a Sleeper",
      "score": 6,
      "user": "jeffkastner",
      "review_date": {
        "month": 12,
        "year": 2013,
        "day": 19,
        "__type__": "datetime.date"
      }
    },
    {
      "contents": "Hard punching and straight forward film delivers",
      "score": 8,
      "user": "bain0038",
      "review_date": {
        "month": 12,
        "year": 2013,
        "day": 7,
        "__type__": "datetime.date"
      }
    },
    {
      "contents": "Like A Meal Without Wine",
      "score": 7,
      "user": "kevandeb",
      "review_date": {
        "month": 1,
        "year": 2014,
        "day": 3,
        "__type__": "datetime.date"
      }
    },
    {
      "contents": "Not buying it",
      "score": 5,
      "user": "FrostyChud",
      "review_date": {
        "month": 1,
        "year": 2014,
        "day": 22,
        "__type__": "datetime.date"
      }
    },
    {
      "contents": "What a disappointment",
      "score": 5,
      "user": "joshua kit",
      "review_date": {
        "month": 12,
        "year": 2013,
        "day": 29,
        "__type__": "datetime.date"
      }
    },
    {
      "contents": "Much Too Slow Burn To Spark Complete Interest",
      "score": 4,
      "user": "cultfilmfreaksdotcom",
      "review_date": {
        "month": 12,
        "year": 2013,
        "day": 6,
        "__type__": "datetime.date"
      }
    },
    {
      "contents": "average at best",
      "score": 5,
      "user": "jason-mcparland",
      "review_date": {
        "month": 12,
        "year": 2013,
        "day": 30,
        "__type__": "datetime.date"
      }
    },
    {
      "contents": "not a movie it's an acting clinic",
      "score": 8,
      "user": "A_Different_Drummer",
      "review_date": {
        "month": 12,
        "year": 2013,
        "day": 26,
        "__type__": "datetime.date"
      }
    },
    {
      "contents": "Are you kidding me?",
      "score": 1,
      "user": "jeremyderifield",
      "review_date": {
        "month": 3,
        "year": 2014,
        "day": 11,
        "__type__": "datetime.date"
      }
    },
    {
      "contents": "An authentic and good-looking film that rings completely untrue in its characterizations and script",
      "score": 4,
      "user": "Matt Greene",
      "review_date": {
        "month": 12,
        "year": 2013,
        "day": 14,
        "__type__": "datetime.date"
      }
    },
    {
      "contents": "Nicely acted below par written story",
      "score": 5,
      "user": "Ruaridh Currie",
      "review_date": {
        "month": 4,
        "year": 2014,
        "day": 26,
        "__type__": "datetime.date"
      }
    },
    {
      "contents": "Great content, just not the tightest story.",
      "score": 8,
      "user": "Jesse Boland",
      "review_date": {
        "month": 12,
        "year": 2013,
        "day": 24,
        "__type__": "datetime.date"
      }
    },
    {
      "contents": "Bale and Harrelson at their best.",
      "score": 6,
      "user": "Thiea Arantxa",
      "review_date": {
        "month": 1,
        "year": 2014,
        "day": 11,
        "__type__": "datetime.date"
      }
    },
    {
      "contents": "Don't waste your time with this, even with the great actors....",
      "score": 1,
      "user": "colonel52",
      "review_date": {
        "month": 3,
        "year": 2014,
        "day": 4,
        "__type__": "datetime.date"
      }
    },
    {
      "contents": "Excellent acting, story lacking",
      "score": 5,
      "user": "Denise Van Winkle",
      "review_date": {
        "month": 12,
        "year": 2013,
        "day": 21,
        "__type__": "datetime.date"
      }
    },
    {
      "contents": "Predictable Plot, Weak Points of Attachment",
      "score": 4,
      "user": "The W Factor Critics",
      "review_date": {
        "month": 6,
        "year": 2014,
        "day": 16,
        "__type__": "datetime.date"
      }
    },
    {
      "contents": "Too unpleasant - an inferior Winter's Bone",
      "score": 2,
      "user": "phd_travel",
      "review_date": {
        "month": 6,
        "year": 2014,
        "day": 6,
        "__type__": "datetime.date"
      }
    },
    {
      "contents": "PTSD... again?",
      "score": 1,
      "user": "Dave Foy",
      "review_date": {
        "month": 8,
        "year": 2014,
        "day": 3,
        "__type__": "datetime.date"
      }
    },
    {
      "contents": "Excellent performances, but weak and manipulative screenplay",
      "score": 5,
      "user": "estebangonzalez10",
      "review_date": {
        "month": 1,
        "year": 2014,
        "day": 15,
        "__type__": "datetime.date"
      }
    },
    {
      "contents": "Powerful but lacks depth",
      "score": 6,
      "user": "Chris L",
      "review_date": {
        "month": 1,
        "year": 2014,
        "day": 26,
        "__type__": "datetime.date"
      }
    },
    {
      "contents": "Great performance, but not the kind that you would enjoy for 116 boring minutes",
      "score": 2,
      "user": "Otto Kantaria",
      "review_date": {
        "month": 2,
        "year": 2014,
        "day": 27,
        "__type__": "datetime.date"
      }
    },
    {
      "contents": "Just not an important story",
      "score": 4,
      "user": "bravesfanc",
      "review_date": {
        "month": 1,
        "year": 2015,
        "day": 6,
        "__type__": "datetime.date"
      }
    },
    {
      "contents": "Awful movie",
      "score": 3,
      "user": "Simone Di Bella",
      "review_date": {
        "month": 9,
        "year": 2014,
        "day": 2,
        "__type__": "datetime.date"
      }
    },
    {
      "contents": "Miscast and Misguided",
      "score": 3,
      "user": "greg-52-418654",
      "review_date": {
        "month": 7,
        "year": 2014,
        "day": 12,
        "__type__": "datetime.date"
      }
    },
    {
      "contents": "not as good as expected",
      "score": 4,
      "user": "Abdelrahman Elghazawy",
      "review_date": {
        "month": 3,
        "year": 2014,
        "day": 5,
        "__type__": "datetime.date"
      }
    },
    {
      "contents": "A Waste of 2 Hours",
      "score": 4,
      "user": "Filmy2020",
      "review_date": {
        "month": 3,
        "year": 2014,
        "day": 22,
        "__type__": "datetime.date"
      }
    },
    {
      "contents": "An almost complete waste of time!",
      "score": 3,
      "user": "andersb1976",
      "review_date": {
        "month": 2,
        "year": 2014,
        "day": 28,
        "__type__": "datetime.date"
      }
    },
    {
      "contents": "Slow, wrenching exploration of....nothing",
      "score": 5,
      "user": "Liam Blackburn",
      "review_date": {
        "month": 12,
        "year": 2013,
        "day": 22,
        "__type__": "datetime.date"
      }
    },
    {
      "contents": "Acting good but the rest, horrible",
      "score": 2,
      "user": "valnaples",
      "review_date": {
        "month": 12,
        "year": 2013,
        "day": 28,
        "__type__": "datetime.date"
      }
    },
    {
      "contents": "Painfully slow",
      "score": 1,
      "user": "wesflynn",
      "review_date": {
        "month": 1,
        "year": 2014,
        "day": 18,
        "__type__": "datetime.date"
      }
    },
    {
      "contents": "Out of the Furnace: Bale's Return a Slow Burn",
      "score": 4,
      "user": "Brick Movie Reviews",
      "review_date": {
        "month": 12,
        "year": 2013,
        "day": 9,
        "__type__": "datetime.date"
      }
    },
    {
      "contents": "Do not watch, You will ask for your money and time back.",
      "score": 1,
      "user": "Wesley MacKay",
      "review_date": {
        "month": 12,
        "year": 2013,
        "day": 9,
        "__type__": "datetime.date"
      }
    },
    {
      "contents": "Such a waste of good actors",
      "score": 4,
      "user": "ilkazapata",
      "review_date": {
        "month": 1,
        "year": 2017,
        "day": 2,
        "__type__": "datetime.date"
      }
    },
    {
      "contents": "All-too-familiar mood piece",
      "score": 6,
      "user": "Leofwine_draca",
      "review_date": {
        "month": 7,
        "year": 2016,
        "day": 28,
        "__type__": "datetime.date"
      }
    },
    {
      "contents": "Sound Sucks!",
      "score": 7,
      "user": "Ted Polte (theglen01@yahoo.ca)",
      "review_date": {
        "month": 7,
        "year": 2016,
        "day": 26,
        "__type__": "datetime.date"
      }
    },
    {
      "contents": "Average despite the talented cast",
      "score": 7,
      "user": "juneebuggy",
      "review_date": {
        "month": 7,
        "year": 2016,
        "day": 20,
        "__type__": "datetime.date"
      }
    },
    {
      "contents": "like a lukewarm breeze",
      "score": 2,
      "user": "dominik-begere",
      "review_date": {
        "month": 3,
        "year": 2016,
        "day": 29,
        "__type__": "datetime.date"
      }
    },
    {
      "contents": "Out of Purpose",
      "score": 6,
      "user": "WaveWC64",
      "review_date": {
        "month": 1,
        "year": 2016,
        "day": 21,
        "__type__": "datetime.date"
      }
    },
    {
      "contents": "Again, the pacing of this revenge flick is completely off and might have worked better as a short film, rather than a feature length.",
      "score": 3,
      "user": "Bryan Kluger",
      "review_date": {
        "month": 8,
        "year": 2015,
        "day": 22,
        "__type__": "datetime.date"
      }
    },
    {
      "contents": "Laughable - Spoilers",
      "score": 3,
      "user": "indiedavid",
      "review_date": {
        "month": 7,
        "year": 2015,
        "day": 29,
        "__type__": "datetime.date"
      }
    },
    {
      "contents": "Casey Affleck is a rose between all these furnaces; awkward bro furnaces.",
      "score": 4,
      "user": "Ben Parker (ben.cheshire@optusnet.com.au)",
      "review_date": {
        "month": 5,
        "year": 2015,
        "day": 14,
        "__type__": "datetime.date"
      }
    },
    {
      "contents": "A Thriller in Name Only",
      "score": 5,
      "user": " (bob-rutzel-1)",
      "review_date": {
        "month": 4,
        "year": 2014,
        "day": 12,
        "__type__": "datetime.date"
      }
    },
    {
      "contents": "BTW there's nothing offensive in this film (for anyone)",
      "score": 6,
      "user": "Arnav Goswami",
      "review_date": {
        "month": 2,
        "year": 2014,
        "day": 27,
        "__type__": "datetime.date"
      }
    },
    {
      "contents": "stale, and anticlimactic",
      "score": 6,
      "user": "nitramd2000",
      "review_date": {
        "month": 7,
        "year": 2014,
        "day": 18,
        "__type__": "datetime.date"
      }
    },
    {
      "contents": "Excellent character-driven film",
      "score": 8,
      "user": "punishable-by-death",
      "review_date": {
        "month": 3,
        "year": 2014,
        "day": 30,
        "__type__": "datetime.date"
      }
    },
    {
      "contents": "If you are from the rust-belt, you will relate to this film in some way.",
      "score": 9,
      "user": "AngryWarrior",
      "review_date": {
        "month": 3,
        "year": 2014,
        "day": 18,
        "__type__": "datetime.date"
      }
    },
    {
      "contents": "Why didn't they nominate Bale for this part ?",
      "score": 7,
      "user": "Peter Pluymers (peterp@cyberdude.com)",
      "review_date": {
        "month": 3,
        "year": 2014,
        "day": 14,
        "__type__": "datetime.date"
      }
    },
    {
      "contents": "weak script and over length = disaster",
      "score": 3,
      "user": "hp-anzinger",
      "review_date": {
        "month": 2,
        "year": 2014,
        "day": 10,
        "__type__": "datetime.date"
      }
    },
    {
      "contents": "The potential was there - just a bit of a let-down in the end.",
      "score": 7,
      "user": "John Kelly",
      "review_date": {
        "month": 12,
        "year": 2013,
        "day": 24,
        "__type__": "datetime.date"
      }
    },
    {
      "contents": "Overrated ... stars don't make a movie. Summary: \"meh\"",
      "score": 4,
      "user": "jij98111",
      "review_date": {
        "month": 1,
        "year": 2014,
        "day": 1,
        "__type__": "datetime.date"
      }
    },
    {
      "contents": "Good acting to compensate for a poor story.",
      "score": 3,
      "user": "Andr\u00c3\u00a9 Guimar\u00c3\u00a3es",
      "review_date": {
        "month": 12,
        "year": 2013,
        "day": 29,
        "__type__": "datetime.date"
      }
    },
    {
      "contents": "Parts Poorly Woven Into Banality. \u2666 40%",
      "score": 4,
      "user": "Tejas Nair",
      "review_date": {
        "month": 12,
        "year": 2013,
        "day": 22,
        "__type__": "datetime.date"
      }
    },
    {
      "contents": "Pretentious piece of crap",
      "score": 1,
      "user": "chris-5913",
      "review_date": {
        "month": 1,
        "year": 2014,
        "day": 1,
        "__type__": "datetime.date"
      }
    },
    {
      "contents": "Great acting, Boring film",
      "score": 2,
      "user": "Aggiemba95",
      "review_date": {
        "month": 12,
        "year": 2013,
        "day": 6,
        "__type__": "datetime.date"
      }
    },
    {
      "contents": "Poor People Wash",
      "score": 3,
      "user": "ehmalheur",
      "review_date": {
        "month": 12,
        "year": 2013,
        "day": 12,
        "__type__": "datetime.date"
      }
    },
    {
      "contents": "slow, slow...........slow",
      "score": 4,
      "user": "myerzzz",
      "review_date": {
        "month": 12,
        "year": 2013,
        "day": 13,
        "__type__": "datetime.date"
      }
    },
    {
      "contents": "Grittiness was Only Purpose",
      "score": 6,
      "user": "dansview",
      "review_date": {
        "month": 11,
        "year": 2015,
        "day": 8,
        "__type__": "datetime.date"
      }
    },
    {
      "contents": "An average dramatic film",
      "score": 5,
      "user": "alindsay-al",
      "review_date": {
        "month": 8,
        "year": 2015,
        "day": 31,
        "__type__": "datetime.date"
      }
    },
    {
      "contents": "Grim, Post-Industrial USA",
      "score": 6,
      "user": "HomeinIndiana",
      "review_date": {
        "month": 2,
        "year": 2015,
        "day": 1,
        "__type__": "datetime.date"
      }
    },
    {
      "contents": "Tries too hard to be powerful, but..",
      "score": 6,
      "user": "faizanjehangir",
      "review_date": {
        "month": 12,
        "year": 2014,
        "day": 5,
        "__type__": "datetime.date"
      }
    },
    {
      "contents": "Pretty Empty",
      "score": 6,
      "user": "Scott McIlroy",
      "review_date": {
        "month": 12,
        "year": 2014,
        "day": 1,
        "__type__": "datetime.date"
      }
    },
    {
      "contents": "A movie that promises yet never quite delivers",
      "score": 6,
      "user": "nathansmithba",
      "review_date": {
        "month": 11,
        "year": 2014,
        "day": 29,
        "__type__": "datetime.date"
      }
    },
    {
      "contents": "Drama: The Movie",
      "score": 5,
      "user": "TheMarwood",
      "review_date": {
        "month": 5,
        "year": 2014,
        "day": 15,
        "__type__": "datetime.date"
      }
    },
    {
      "contents": "Miscasting\u0085Typecasting\u0085Artificial",
      "score": 6,
      "user": "LeonLouisRicci",
      "review_date": {
        "month": 4,
        "year": 2014,
        "day": 9,
        "__type__": "datetime.date"
      }
    },
    {
      "contents": "A film with strong material, but not the best direction to guide it in",
      "score": 7,
      "user": "davideo-2",
      "review_date": {
        "month": 9,
        "year": 2014,
        "day": 23,
        "__type__": "datetime.date"
      }
    },
    {
      "contents": "Very watchable grim drama",
      "score": 7,
      "user": "Adam Peters",
      "review_date": {
        "month": 9,
        "year": 2014,
        "day": 10,
        "__type__": "datetime.date"
      }
    },
    {
      "contents": "Generic storyline saved by fantastic acting...",
      "score": 6,
      "user": "Paul Magne Haakonsen",
      "review_date": {
        "month": 8,
        "year": 2014,
        "day": 10,
        "__type__": "datetime.date"
      }
    },
    {
      "contents": "A Film That Had Potential But Ends Up Plain",
      "score": 6,
      "user": "TheFilmGuy1",
      "review_date": {
        "month": 8,
        "year": 2014,
        "day": 6,
        "__type__": "datetime.date"
      }
    },
    {
      "contents": "Some great acting turns lost in a uneven story",
      "score": 6,
      "user": "eddie_baggins",
      "review_date": {
        "month": 7,
        "year": 2014,
        "day": 28,
        "__type__": "datetime.date"
      }
    },
    {
      "contents": "Slow Burner with decent acting but overall fails to deliver.",
      "score": 6,
      "user": "DavidHT",
      "review_date": {
        "month": 7,
        "year": 2014,
        "day": 20,
        "__type__": "datetime.date"
      }
    },
    {
      "contents": "really a 7 but needs some love on here",
      "score": 8,
      "user": "Raoul Duke",
      "review_date": {
        "month": 7,
        "year": 2014,
        "day": 17,
        "__type__": "datetime.date"
      }
    },
    {
      "contents": "'Furnace' is a slow burn",
      "score": 7,
      "user": "Fluke_Skywalker",
      "review_date": {
        "month": 7,
        "year": 2014,
        "day": 2,
        "__type__": "datetime.date"
      }
    },
    {
      "contents": "Average revenge movie! 5/10",
      "score": 5,
      "user": "leonblackwood",
      "review_date": {
        "month": 6,
        "year": 2014,
        "day": 9,
        "__type__": "datetime.date"
      }
    },
    {
      "contents": "Good team they got, but...",
      "score": 7,
      "user": "elgabote",
      "review_date": {
        "month": 5,
        "year": 2014,
        "day": 26,
        "__type__": "datetime.date"
      }
    },
    {
      "contents": "It has its issues but it's still a decent film...",
      "score": 6,
      "user": "RevRonster",
      "review_date": {
        "month": 4,
        "year": 2014,
        "day": 23,
        "__type__": "datetime.date"
      }
    },
    {
      "contents": "Apparently underrated movie.",
      "score": 9,
      "user": "John Black",
      "review_date": {
        "month": 4,
        "year": 2014,
        "day": 4,
        "__type__": "datetime.date"
      }
    },
    {
      "contents": "Camus' Stranger was felt in this amazing movie",
      "score": 10,
      "user": "botelho_as",
      "review_date": {
        "month": 3,
        "year": 2014,
        "day": 30,
        "__type__": "datetime.date"
      }
    },
    {
      "contents": "Under-noticed",
      "score": 7,
      "user": "cinematic_aficionado (cinematokrisis@gmail.com)",
      "review_date": {
        "month": 3,
        "year": 2014,
        "day": 28,
        "__type__": "datetime.date"
      }
    },
    {
      "contents": "'Working for a living? I gave my life for this country and what's it done for me?'",
      "score": 7,
      "user": "gradyharp",
      "review_date": {
        "month": 3,
        "year": 2014,
        "day": 16,
        "__type__": "datetime.date"
      }
    },
    {
      "contents": "Christian Bale Delivers A Compelling Performance!",
      "score": 7,
      "user": "nama chakravorty",
      "review_date": {
        "month": 3,
        "year": 2014,
        "day": 16,
        "__type__": "datetime.date"
      }
    },
    {
      "contents": "I loved the human aspect of this film",
      "score": 8,
      "user": "gemini_dremz",
      "review_date": {
        "month": 3,
        "year": 2014,
        "day": 14,
        "__type__": "datetime.date"
      }
    },
    {
      "contents": "Weak ending underwhelms, an otherwise really good movie",
      "score": 7,
      "user": "pcrprimer",
      "review_date": {
        "month": 3,
        "year": 2014,
        "day": 7,
        "__type__": "datetime.date"
      }
    },
    {
      "contents": "A Skillful But Slow-Paced Crime Flick.",
      "score": 7,
      "user": "Govind Nair",
      "review_date": {
        "month": 3,
        "year": 2014,
        "day": 7,
        "__type__": "datetime.date"
      }
    },
    {
      "contents": "Great Movie, although a poor end...",
      "score": 8,
      "user": "Rodri Alves",
      "review_date": {
        "month": 3,
        "year": 2014,
        "day": 7,
        "__type__": "datetime.date"
      }
    },
    {
      "contents": "A harsh subject  in a solid film",
      "score": 8,
      "user": "johntheholder",
      "review_date": {
        "month": 3,
        "year": 2014,
        "day": 2,
        "__type__": "datetime.date"
      }
    },
    {
      "contents": "Out of the Furnace: you really have to watch it.",
      "score": 9,
      "user": "niutta-enrico",
      "review_date": {
        "month": 3,
        "year": 2014,
        "day": 2,
        "__type__": "datetime.date"
      }
    },
    {
      "contents": "Infuriatingly bad, but also infuriatingly good.",
      "score": 5,
      "user": "Matt West",
      "review_date": {
        "month": 12,
        "year": 2013,
        "day": 19,
        "__type__": "datetime.date"
      }
    },
    {
      "contents": "Slow Burner",
      "score": 9,
      "user": "kosmasp",
      "review_date": {
        "month": 8,
        "year": 2014,
        "day": 15,
        "__type__": "datetime.date"
      }
    },
    {
      "contents": "Mumbling entire movie.",
      "score": 4,
      "user": "jon-wagner",
      "review_date": {
        "month": 4,
        "year": 2014,
        "day": 30,
        "__type__": "datetime.date"
      }
    },
    {
      "contents": "Should have stayed in the furnace.",
      "score": 4,
      "user": "johnnyringo-979-407909",
      "review_date": {
        "month": 4,
        "year": 2014,
        "day": 25,
        "__type__": "datetime.date"
      }
    },
    {
      "contents": "Hard to follow, horrible story-writing, decent acting",
      "score": 1,
      "user": "lc023",
      "review_date": {
        "month": 4,
        "year": 2014,
        "day": 19,
        "__type__": "datetime.date"
      }
    },
    {
      "contents": "What to Expect: Out of the Furnace",
      "score": 8,
      "user": "Film Watchin Fool",
      "review_date": {
        "month": 4,
        "year": 2014,
        "day": 12,
        "__type__": "datetime.date"
      }
    },
    {
      "contents": "The movie is real",
      "score": 10,
      "user": "james-rainie",
      "review_date": {
        "month": 4,
        "year": 2014,
        "day": 9,
        "__type__": "datetime.date"
      }
    },
    {
      "contents": "Supposed to be great",
      "score": 2,
      "user": "Caio Andrade",
      "review_date": {
        "month": 3,
        "year": 2014,
        "day": 29,
        "__type__": "datetime.date"
      }
    },
    {
      "contents": "Casey & Harrelson steal the show over Bale's strong presence",
      "score": 8,
      "user": "Reno Rangan",
      "review_date": {
        "month": 3,
        "year": 2014,
        "day": 18,
        "__type__": "datetime.date"
      }
    },
    {
      "contents": "Good acting but predictable plot",
      "score": 6,
      "user": "Ankush Jaggi",
      "review_date": {
        "month": 1,
        "year": 2014,
        "day": 25,
        "__type__": "datetime.date"
      }
    },
    {
      "contents": "A tight story would have made it a classic movie.Yet watchable",
      "score": 7,
      "user": "rashpace40",
      "review_date": {
        "month": 1,
        "year": 2014,
        "day": 2,
        "__type__": "datetime.date"
      }
    },
    {
      "contents": "Release Me.....",
      "score": 8,
      "user": "Adam Sentiff (Asentiff2004@yahoo.com)",
      "review_date": {
        "month": 12,
        "year": 2013,
        "day": 30,
        "__type__": "datetime.date"
      }
    },
    {
      "contents": "Dark and oppressive, with splendid acting",
      "score": 7,
      "user": "Bene Cumb",
      "review_date": {
        "month": 12,
        "year": 2013,
        "day": 29,
        "__type__": "datetime.date"
      }
    },
    {
      "contents": "good start turns into a sleeper",
      "score": 3,
      "user": "ajschuetze54",
      "review_date": {
        "month": 5,
        "year": 2014,
        "day": 23,
        "__type__": "datetime.date"
      }
    },
    {
      "contents": "Some mesmerising performances in this story about Americans on the ropes.",
      "score": 8,
      "user": "garretthunter",
      "review_date": {
        "month": 1,
        "year": 2014,
        "day": 17,
        "__type__": "datetime.date"
      }
    },
    {
      "contents": "Ultra Dark Story With Two Academy Award Level Performances",
      "score": 8,
      "user": "AudioFileZ",
      "review_date": {
        "month": 1,
        "year": 2014,
        "day": 2,
        "__type__": "datetime.date"
      }
    },
    {
      "contents": "Good movie. Great performances by all actors.",
      "score": 9,
      "user": "kathy",
      "review_date": {
        "month": 12,
        "year": 2013,
        "day": 22,
        "__type__": "datetime.date"
      }
    },
    {
      "contents": "Somber Revenge",
      "score": 8,
      "user": "space_base",
      "review_date": {
        "month": 1,
        "year": 2014,
        "day": 8,
        "__type__": "datetime.date"
      }
    },
    {
      "contents": "Bale and Affleck elevate a decent film in competent hands.",
      "score": 7,
      "user": "Sergeant_Tibbs",
      "review_date": {
        "month": 12,
        "year": 2013,
        "day": 27,
        "__type__": "datetime.date"
      }
    },
    {
      "contents": "Great Until the End.",
      "score": 7,
      "user": "woelfleriver",
      "review_date": {
        "month": 12,
        "year": 2013,
        "day": 7,
        "__type__": "datetime.date"
      }
    },
    {
      "contents": "Good Cast But Wait Until it Hits Cable",
      "score": 5,
      "user": "steve beard (stevendbeard@aol.com)",
      "review_date": {
        "month": 12,
        "year": 2013,
        "day": 6,
        "__type__": "datetime.date"
      }
    },
    {
      "contents": "pants",
      "score": 1,
      "user": "fawcett1984",
      "review_date": {
        "month": 12,
        "year": 2013,
        "day": 25,
        "__type__": "datetime.date"
      }
    },
    {
      "contents": "Not just slow, but moves at a glacial pace. And feels like a TV movie",
      "score": 4,
      "user": "quinnox-1",
      "review_date": {
        "month": 12,
        "year": 2013,
        "day": 8,
        "__type__": "datetime.date"
      }
    },
    {
      "contents": "Could've been a contender, but ended leaving ??????s",
      "score": 3,
      "user": "jr9547",
      "review_date": {
        "month": 12,
        "year": 2013,
        "day": 6,
        "__type__": "datetime.date"
      }
    },
    {
      "contents": "Depressing",
      "score": 1,
      "user": "zzyzx000-124-271558",
      "review_date": {
        "month": 12,
        "year": 2013,
        "day": 20,
        "__type__": "datetime.date"
      }
    },
    {
      "contents": "Gritty. Dark. Grim. Not a bad movie.",
      "score": 7,
      "user": "allyatherton",
      "review_date": {
        "month": 7,
        "year": 2016,
        "day": 27,
        "__type__": "datetime.date"
      }
    },
    {
      "contents": "The Ultimate Movie Review! - http://tss5078.blogspot.com - @tss5078",
      "score": 8,
      "user": "Tss5078",
      "review_date": {
        "month": 4,
        "year": 2016,
        "day": 7,
        "__type__": "datetime.date"
      }
    },
    {
      "contents": "Bale Fires Up.",
      "score": 9,
      "user": "Python Hyena",
      "review_date": {
        "month": 1,
        "year": 2016,
        "day": 13,
        "__type__": "datetime.date"
      }
    },
    {
      "contents": "depressing film",
      "score": 6,
      "user": "blanche-2",
      "review_date": {
        "month": 12,
        "year": 2015,
        "day": 26,
        "__type__": "datetime.date"
      }
    },
    {
      "contents": "\"Out of the Furnace\" brings an intense heat that's hard to forget.",
      "score": 9,
      "user": "Dave McClain (dave-mcclain@hotmail.com)",
      "review_date": {
        "month": 10,
        "year": 2015,
        "day": 29,
        "__type__": "datetime.date"
      }
    },
    {
      "contents": "Out of the Furnace",
      "score": 7,
      "user": "JohnnyWeissmuller",
      "review_date": {
        "month": 10,
        "year": 2015,
        "day": 25,
        "__type__": "datetime.date"
      }
    },
    {
      "contents": "Mass shooting, one at a time",
      "score": 8,
      "user": "sw_florida",
      "review_date": {
        "month": 8,
        "year": 2015,
        "day": 27,
        "__type__": "datetime.date"
      }
    },
    {
      "contents": "A well acted movie!!!!!",
      "score": 7,
      "user": "rajatdahiyax",
      "review_date": {
        "month": 8,
        "year": 2015,
        "day": 1,
        "__type__": "datetime.date"
      }
    },
    {
      "contents": "Dark and Moody",
      "score": 7,
      "user": "Uriah43",
      "review_date": {
        "month": 4,
        "year": 2015,
        "day": 1,
        "__type__": "datetime.date"
      }
    },
    {
      "contents": "Down to earth feel",
      "score": 7,
      "user": "Ole Sandbaek Joergensen",
      "review_date": {
        "month": 2,
        "year": 2015,
        "day": 22,
        "__type__": "datetime.date"
      }
    },
    {
      "contents": "Very underrated and great film!!",
      "score": 10,
      "user": "mattralston1990",
      "review_date": {
        "month": 2,
        "year": 2015,
        "day": 9,
        "__type__": "datetime.date"
      }
    },
    {
      "contents": "A good picture about a small subject",
      "score": 7,
      "user": "vandelour",
      "review_date": {
        "month": 1,
        "year": 2015,
        "day": 24,
        "__type__": "datetime.date"
      }
    },
    {
      "contents": "The Springsteen of Cinema!",
      "score": 9,
      "user": "g-bodyl",
      "review_date": {
        "month": 1,
        "year": 2015,
        "day": 13,
        "__type__": "datetime.date"
      }
    },
    {
      "contents": "Bale shows up, Harrelson and Affleck at their best",
      "score": 8,
      "user": "nevans1984",
      "review_date": {
        "month": 1,
        "year": 2015,
        "day": 12,
        "__type__": "datetime.date"
      }
    },
    {
      "contents": "More ins than outs here!",
      "score": 8,
      "user": "meeza (themeezaman@hotmail.com)",
      "review_date": {
        "month": 1,
        "year": 2015,
        "day": 2,
        "__type__": "datetime.date"
      }
    },
    {
      "contents": "Intense Gripping Drama",
      "score": 7,
      "user": "Floated2",
      "review_date": {
        "month": 12,
        "year": 2014,
        "day": 24,
        "__type__": "datetime.date"
      }
    },
    {
      "contents": "Yet another movie that's gotten lower scores than it should have!",
      "score": 10,
      "user": "Maverick Wolfe",
      "review_date": {
        "month": 11,
        "year": 2014,
        "day": 29,
        "__type__": "datetime.date"
      }
    },
    {
      "contents": "Well-performed, but underwhelming drama that doesn't live up to its existential themes",
      "score": 7,
      "user": "brchthethird",
      "review_date": {
        "month": 11,
        "year": 2014,
        "day": 14,
        "__type__": "datetime.date"
      }
    },
    {
      "contents": "\"You let me worry about who's a nasty son of a b....\"",
      "score": 8,
      "user": "classicsoncall",
      "review_date": {
        "month": 10,
        "year": 2014,
        "day": 26,
        "__type__": "datetime.date"
      }
    },
    {
      "contents": "Two hours edge-of-seat stuff",
      "score": 8,
      "user": "Thomas (filmreviews@web.de)",
      "review_date": {
        "month": 9,
        "year": 2014,
        "day": 16,
        "__type__": "datetime.date"
      }
    },
    {
      "contents": "Attempt to portray raw humanity at close quarters",
      "score": 6,
      "user": "AkelaLoneWolf",
      "review_date": {
        "month": 6,
        "year": 2014,
        "day": 21,
        "__type__": "datetime.date"
      }
    },
    {
      "contents": "well worth the watch",
      "score": 8,
      "user": "lagocasa",
      "review_date": {
        "month": 6,
        "year": 2014,
        "day": 21,
        "__type__": "datetime.date"
      }
    },
    {
      "contents": "Christian Bale seeks to avenge his brother's (Casey Affleck's) murder by killing Woody Harrelson",
      "score": 5,
      "user": "msroz",
      "review_date": {
        "month": 3,
        "year": 2014,
        "day": 20,
        "__type__": "datetime.date"
      }
    },
    {
      "contents": "The movie is very gritty and realistic but I never really got all the way involved in it. Great cast but disappointing.",
      "score": 6,
      "user": "Tony Heck (cosmo_tiger@hotmail.com)",
      "review_date": {
        "month": 3,
        "year": 2014,
        "day": 10,
        "__type__": "datetime.date"
      }
    },
    {
      "contents": "A slow burn that never really catches fire, but it's compelling viewing nonetheless.",
      "score": 6,
      "user": "shawneofthedead",
      "review_date": {
        "month": 2,
        "year": 2014,
        "day": 19,
        "__type__": "datetime.date"
      }
    },
    {
      "contents": "Out of the frying pan and into the fire",
      "score": 6,
      "user": "rooee",
      "review_date": {
        "month": 2,
        "year": 2014,
        "day": 2,
        "__type__": "datetime.date"
      }
    },
    {
      "contents": "Bale on top form",
      "score": 9,
      "user": "jonesthetaxi",
      "review_date": {
        "month": 10,
        "year": 2014,
        "day": 29,
        "__type__": "datetime.date"
      }
    },
    {
      "contents": "Like a loose cannon.",
      "score": 7,
      "user": "Siddharth kalkal",
      "review_date": {
        "month": 9,
        "year": 2014,
        "day": 28,
        "__type__": "datetime.date"
      }
    },
    {
      "contents": "great drama with an ending to forget",
      "score": 8,
      "user": "antoniotierno",
      "review_date": {
        "month": 9,
        "year": 2014,
        "day": 2,
        "__type__": "datetime.date"
      }
    },
    {
      "contents": "\u0085But Not Into the Fire",
      "score": 7,
      "user": "taikung1",
      "review_date": {
        "month": 7,
        "year": 2014,
        "day": 12,
        "__type__": "datetime.date"
      }
    },
    {
      "contents": "Brilliant and intense entertainment.",
      "score": 10,
      "user": "AJSteele",
      "review_date": {
        "month": 6,
        "year": 2014,
        "day": 17,
        "__type__": "datetime.date"
      }
    },
    {
      "contents": "A Relevant Film in Tough Economic Times",
      "score": 8,
      "user": "Tariq  Hossenbux (tariq-hossenbux)",
      "review_date": {
        "month": 6,
        "year": 2014,
        "day": 1,
        "__type__": "datetime.date"
      }
    },
    {
      "contents": "A revenge movie with soul.",
      "score": 7,
      "user": "Vis Chetty",
      "review_date": {
        "month": 4,
        "year": 2014,
        "day": 15,
        "__type__": "datetime.date"
      }
    },
    {
      "contents": "Falls far short of the meaningful film I suspect it thinks it is. Thriller? Not in a million years",
      "score": 5,
      "user": "patrick powell",
      "review_date": {
        "month": 2,
        "year": 2014,
        "day": 16,
        "__type__": "datetime.date"
      }
    },
    {
      "contents": "You Can't Be Doing This",
      "score": 5,
      "user": "ritera1",
      "review_date": {
        "month": 1,
        "year": 2014,
        "day": 3,
        "__type__": "datetime.date"
      }
    },
    {
      "contents": "I really really wanted to like it.",
      "score": 5,
      "user": "nhietter",
      "review_date": {
        "month": 1,
        "year": 2014,
        "day": 1,
        "__type__": "datetime.date"
      }
    },
    {
      "contents": "Great performances by Bale and Harrelson - dark and edgy",
      "score": 7,
      "user": "graupepillard",
      "review_date": {
        "month": 12,
        "year": 2013,
        "day": 31,
        "__type__": "datetime.date"
      }
    },
    {
      "contents": "Real slice of life. Nearly perfect acting",
      "score": 10,
      "user": "scottlmoore",
      "review_date": {
        "month": 5,
        "year": 2014,
        "day": 12,
        "__type__": "datetime.date"
      }
    },
    {
      "contents": "The cinematic equivalent of a slowly simmering pan of acid.",
      "score": 8,
      "user": "TheSquiss",
      "review_date": {
        "month": 1,
        "year": 2014,
        "day": 21,
        "__type__": "datetime.date"
      }
    },
    {
      "contents": "Gritty Tale of Modern America",
      "score": 9,
      "user": "aharmas",
      "review_date": {
        "month": 1,
        "year": 2014,
        "day": 9,
        "__type__": "datetime.date"
      }
    },
    {
      "contents": "Wasted Bales talent",
      "score": 6,
      "user": "virtue_srb",
      "review_date": {
        "month": 1,
        "year": 2014,
        "day": 1,
        "__type__": "datetime.date"
      }
    },
    {
      "contents": "How are you going to pick Forest Whitaker over Christian Bale?!",
      "score": 5,
      "user": "Markus Emilio Robinson",
      "review_date": {
        "month": 12,
        "year": 2013,
        "day": 12,
        "__type__": "datetime.date"
      }
    },
    {
      "contents": "Solid action and great casting but nothing really new",
      "score": 7,
      "user": "hudini669",
      "review_date": {
        "month": 1,
        "year": 2014,
        "day": 4,
        "__type__": "datetime.date"
      }
    },
    {
      "contents": "Very Strong",
      "score": 9,
      "user": "Tim Davis",
      "review_date": {
        "month": 12,
        "year": 2013,
        "day": 20,
        "__type__": "datetime.date"
      }
    },
    {
      "contents": "\"Am I supposed to be scared of him . . . \"",
      "score": 8,
      "user": "cricket crockett",
      "review_date": {
        "month": 12,
        "year": 2013,
        "day": 7,
        "__type__": "datetime.date"
      }
    },
    {
      "contents": "A Typical Revenge Film With Great Actors & Performances But Half Baked Script",
      "score": 5,
      "user": "M MALIK",
      "review_date": {
        "month": 12,
        "year": 2013,
        "day": 28,
        "__type__": "datetime.date"
      }
    },
    {
      "contents": "no wonder box office is so low",
      "score": 1,
      "user": "Mark Enriquez (markenriquez_@hotmail.com)",
      "review_date": {
        "month": 12,
        "year": 2013,
        "day": 23,
        "__type__": "datetime.date"
      }
    },
    {
      "contents": "Great Acting! No Meaning.",
      "score": 6,
      "user": "cdsackett",
      "review_date": {
        "month": 12,
        "year": 2013,
        "day": 9,
        "__type__": "datetime.date"
      }
    },
    {
      "contents": "Don't get burned.",
      "score": 2,
      "user": "Quietb-1",
      "review_date": {
        "month": 12,
        "year": 2013,
        "day": 4,
        "__type__": "datetime.date"
      }
    },
    {
      "contents": "I never write reviews but after seeing some negatives, I had to.",
      "score": 9,
      "user": "nate-m-poole",
      "review_date": {
        "month": 11,
        "year": 2014,
        "day": 18,
        "__type__": "datetime.date"
      }
    },
    {
      "contents": "Brilliant movie",
      "score": 10,
      "user": "851222",
      "review_date": {
        "month": 10,
        "year": 2014,
        "day": 31,
        "__type__": "datetime.date"
      }
    },
    {
      "contents": "Geeky Randy's summary",
      "score": 9,
      "user": "Geeky Randy",
      "review_date": {
        "month": 7,
        "year": 2014,
        "day": 5,
        "__type__": "datetime.date"
      }
    },
    {
      "contents": "A Slow, Simmering and Restrained Film",
      "score": 8,
      "user": "aayush-sharma",
      "review_date": {
        "month": 3,
        "year": 2014,
        "day": 28,
        "__type__": "datetime.date"
      }
    },
    {
      "contents": "Oscar-winning performances abound!",
      "score": 9,
      "user": "timseese-289-40674",
      "review_date": {
        "month": 3,
        "year": 2014,
        "day": 15,
        "__type__": "datetime.date"
      }
    },
    {
      "contents": "The Vidiot Reviews",
      "score": 6,
      "user": "capone666",
      "review_date": {
        "month": 3,
        "year": 2014,
        "day": 13,
        "__type__": "datetime.date"
      }
    },
    {
      "contents": "Ever heard this one before? - An utterly fresh and utterly un-clich\u00e9 revenge drama!",
      "score": 6,
      "user": "Sergio Campanale",
      "review_date": {
        "month": 2,
        "year": 2014,
        "day": 6,
        "__type__": "datetime.date"
      }
    },
    {
      "contents": "Out of the Furnace and onto the ice.",
      "score": 7,
      "user": "ArT_of_InSaNiTy",
      "review_date": {
        "month": 1,
        "year": 2014,
        "day": 30,
        "__type__": "datetime.date"
      }
    },
    {
      "contents": "I just need the money.",
      "score": 6,
      "user": "Andres Benatar Luque (andy@globalheadhunters.net)",
      "review_date": {
        "month": 12,
        "year": 2013,
        "day": 19,
        "__type__": "datetime.date"
      }
    },
    {
      "contents": "A modern day Deer Hunter-esque powerhouse",
      "score": 9,
      "user": "Dan Ashley (DanLives1980)",
      "review_date": {
        "month": 6,
        "year": 2014,
        "day": 2,
        "__type__": "datetime.date"
      }
    },
    {
      "contents": "Very Slow Movie but Surprisingly Isn't Too Much of a Problem,",
      "score": 8,
      "user": "Dillon Harris",
      "review_date": {
        "month": 2,
        "year": 2014,
        "day": 11,
        "__type__": "datetime.date"
      }
    },
    {
      "contents": "Much better than the critics would have you believe.",
      "score": 8,
      "user": "Hugo  Melo",
      "review_date": {
        "month": 2,
        "year": 2014,
        "day": 11,
        "__type__": "datetime.date"
      }
    },
    {
      "contents": "what A performance",
      "score": 10,
      "user": "adrian-525",
      "review_date": {
        "month": 2,
        "year": 2014,
        "day": 8,
        "__type__": "datetime.date"
      }
    },
    {
      "contents": "The masterpiece",
      "score": 9,
      "user": "iwonaso08",
      "review_date": {
        "month": 1,
        "year": 2014,
        "day": 31,
        "__type__": "datetime.date"
      }
    },
    {
      "contents": "A Powerful flick to finish the Year 2013",
      "score": 10,
      "user": "tequila101",
      "review_date": {
        "month": 1,
        "year": 2014,
        "day": 23,
        "__type__": "datetime.date"
      }
    },
    {
      "contents": "Impressive, disturbing, yet incomplete",
      "score": 8,
      "user": "in1984",
      "review_date": {
        "month": 12,
        "year": 2013,
        "day": 25,
        "__type__": "datetime.date"
      }
    },
    {
      "contents": "Slow Tough Grinding movie",
      "score": 7,
      "user": "SnoopyStyle",
      "review_date": {
        "month": 12,
        "year": 2013,
        "day": 20,
        "__type__": "datetime.date"
      }
    },
    {
      "contents": "Rather An Enigma",
      "score": 7,
      "user": "RockoutGlockout117",
      "review_date": {
        "month": 12,
        "year": 2013,
        "day": 16,
        "__type__": "datetime.date"
      }
    },
    {
      "contents": "Excellent standout performances",
      "score": 8,
      "user": "llowry12",
      "review_date": {
        "month": 12,
        "year": 2013,
        "day": 19,
        "__type__": "datetime.date"
      }
    },
    {
      "contents": "Great Story Telling",
      "score": 9,
      "user": "jenyohe12",
      "review_date": {
        "month": 12,
        "year": 2013,
        "day": 30,
        "__type__": "datetime.date"
      }
    },
    {
      "contents": "Excellent film with talented cast and great soundtrack",
      "score": 10,
      "user": "CamyDu",
      "review_date": {
        "month": 12,
        "year": 2013,
        "day": 27,
        "__type__": "datetime.date"
      }
    },
    {
      "contents": "Critics really baffle me sometimes!",
      "score": 8,
      "user": "Hellmant",
      "review_date": {
        "month": 12,
        "year": 2013,
        "day": 14,
        "__type__": "datetime.date"
      }
    },
    {
      "contents": "Excellent!",
      "score": 7,
      "user": "petarmatic",
      "review_date": {
        "month": 12,
        "year": 2013,
        "day": 29,
        "__type__": "datetime.date"
      }
    },
    {
      "contents": "Electrifying But Depressing Drama About Brotherly Love",
      "score": 8,
      "user": "zardoz-13",
      "review_date": {
        "month": 12,
        "year": 2013,
        "day": 14,
        "__type__": "datetime.date"
      }
    },
    {
      "contents": "Out Of The Furnace is a very rare non-commercial masterpiece!",
      "score": 10,
      "user": "Mandeth",
      "review_date": {
        "month": 12,
        "year": 2013,
        "day": 27,
        "__type__": "datetime.date"
      }
    },
    {
      "contents": "Deserves more credit.",
      "score": 10,
      "user": "LastlyKing",
      "review_date": {
        "month": 12,
        "year": 2013,
        "day": 11,
        "__type__": "datetime.date"
      }
    },
    {
      "contents": "'Thunderous Silence' personified",
      "score": 10,
      "user": "coljam21",
      "review_date": {
        "month": 12,
        "year": 2013,
        "day": 6,
        "__type__": "datetime.date"
      }
    },
    {
      "contents": "Characters clearly take precedence here with admirable results.",
      "score": 6,
      "user": "Robyn Nesbitt (nesfilmreviews)",
      "review_date": {
        "month": 12,
        "year": 2013,
        "day": 6,
        "__type__": "datetime.date"
      }
    },
    {
      "contents": "Instant Classic",
      "score": 9,
      "user": "dennis-574-809157 (dennis@paumanokgroup.com)",
      "review_date": {
        "month": 12,
        "year": 2013,
        "day": 6,
        "__type__": "datetime.date"
      }
    },
    {
      "contents": "Well made, but depressing and dispiriting",
      "score": 7,
      "user": "Neil Welch",
      "review_date": {
        "month": 2,
        "year": 2014,
        "day": 7,
        "__type__": "datetime.date"
      }
    },
    {
      "contents": "This rural drama has all the ingredients to be good, but ends up being a disappointment.",
      "score": 7,
      "user": "Amari-Sali",
      "review_date": {
        "month": 12,
        "year": 2013,
        "day": 28,
        "__type__": "datetime.date"
      }
    },
    {
      "contents": "Out Of Luck For A Movie",
      "score": 5,
      "user": " (Richie@RanRightRealty.com)",
      "review_date": {
        "month": 12,
        "year": 2013,
        "day": 23,
        "__type__": "datetime.date"
      }
    },
    {
      "contents": "Hard movie to watch!",
      "score": 7,
      "user": "mm-39",
      "review_date": {
        "month": 12,
        "year": 2013,
        "day": 10,
        "__type__": "datetime.date"
      }
    },
    {
      "contents": "Hardcore, honest, real, gritty. Phenomenal acting, overwhelming hopelessness.",
      "score": 10,
      "user": "Nikola Borissov",
      "review_date": {
        "month": 12,
        "year": 2013,
        "day": 25,
        "__type__": "datetime.date"
      }
    },
    {
      "contents": "Blue-chip cast buoys a tense vengeance drama",
      "score": 8,
      "user": "george.schmidt (gpschmidt67@gmail.com)",
      "review_date": {
        "month": 12,
        "year": 2013,
        "day": 7,
        "__type__": "datetime.date"
      }
    },
    {
      "contents": "A realistic, gritty and brutal character study",
      "score": 9,
      "user": "mweisba4",
      "review_date": {
        "month": 12,
        "year": 2013,
        "day": 10,
        "__type__": "datetime.date"
      }
    },
    {
      "contents": "Another metaphor for the struggle of life these days",
      "score": 9,
      "user": "dwithrow-731-966282",
      "review_date": {
        "month": 12,
        "year": 2013,
        "day": 8,
        "__type__": "datetime.date"
      }
    },
    {
      "contents": "Scott Cooper's 'Out of the Furnace' Loses Steam but Affleck shines...",
      "score": 6,
      "user": "Clayton Davis (Claytondavis@awardscircuit.com)",
      "review_date": {
        "month": 12,
        "year": 2013,
        "day": 1,
        "__type__": "datetime.date"
      }
    },
    {
      "contents": "And Into the Fire",
      "score": 7,
      "user": "David Ferguson (fergusontx@gmail.com)",
      "review_date": {
        "month": 12,
        "year": 2013,
        "day": 14,
        "__type__": "datetime.date"
      }
    },
    {
      "contents": "Boring and dry film, that is still somewhat worth seeing.",
      "score": 7,
      "user": "KineticSeoul",
      "review_date": {
        "month": 12,
        "year": 2013,
        "day": 17,
        "__type__": "datetime.date"
      }
    },
    {
      "contents": "Relentlessly downbeat but still compelling",
      "score": 7,
      "user": "Dan Franzen (dfranzen70)",
      "review_date": {
        "month": 12,
        "year": 2013,
        "day": 9,
        "__type__": "datetime.date"
      }
    },
    {
      "contents": "Out of the Furnace a Solid, But Conventional Crime Drama",
      "score": 7,
      "user": "sgp-12345",
      "review_date": {
        "month": 12,
        "year": 2013,
        "day": 7,
        "__type__": "datetime.date"
      }
    },
    {
      "contents": "Phenomenal performances",
      "score": 9,
      "user": "Tim C.",
      "review_date": {
        "month": 12,
        "year": 2013,
        "day": 31,
        "__type__": "datetime.date"
      }
    },
    {
      "contents": "Waste of talent and resources",
      "score": 2,
      "user": "drjgardner",
      "review_date": {
        "month": 12,
        "year": 2013,
        "day": 7,
        "__type__": "datetime.date"
      }
    },
    {
      "contents": "this is true filmmaking",
      "score": 10,
      "user": "ttron2000",
      "review_date": {
        "month": 12,
        "year": 2013,
        "day": 10,
        "__type__": "datetime.date"
      }
    }
  ],
  "duration": 116,
  "votes_per_demo": {
    "aged_45+": 7323,
    "top_1000_voters": 387,
    "males_under_18": 101,
    "imdb_staff": 10,
    "males_aged_18-29": 26169,
    "imdb_users": 87095,
    "males_aged_45+": 6237,
    "aged_18-29": 29466,
    "us_users": 14764,
    "females_aged_30-44": 3463,
    "males": 66566,
    "females": 7987,
    "females_aged_45+": 959,
    "non-us_users": 43621,
    "females_aged_18-29": 2997,
    "females_under_18": 11,
    "aged_30-44": 34316,
    "aged_under_18": 115,
    "males_aged_30-44": 30453
  },
  "genres": [
    "crime",
    "drama",
    "thriller"
  ],
  "opening_weekend_income_currency": "$",
  "rating_freq": {
    "1": 812,
    "2": 563,
    "3": 1023,
    "4": 2489,
    "5": 6948,
    "6": 19652,
    "7": 30205,
    "8": 16260,
    "9": 4861,
    "10": 4282
  },
  "release_month": "December",
  "budget": 22000000,
  "budget_currency": "$",
  "total_screens": 5335,
  "year": 2013,
  "rating": 6.8,
  "critic_review_count": 290,
  "opening_weekend_date": {
    "month": 12,
    "year": 2013,
    "day": 6,
    "__type__": "datetime.date"
  },
  "name": "Out of the Furnace",
  "user_review_count": 231,
  "avg_screens": 592.7777777777778
}